copymon/__init__.py
copymon/__main__.py
copymon/copymon.py
copymon/main.py
copymon/version.py
copymon-0.1.0.dist-info/LICENSE
copymon-0.1.0.dist-info/METADATA
copymon-0.1.0.dist-info/WHEEL
copymon-0.1.0.dist-info/entry_points.txt
copymon-0.1.0.dist-info/top_level.txt
copymon-0.1.0.dist-info/RECORD
