Metadata-Version: 2.1
Name: copymon
Version: 0.1.0
Summary: Monitor of memory buffers for better estimation of copying time
Home-page: https://github.com/igrek51/copymon
Author: igrek51
Author-email: igrek51.dev@gmail.com
License: MIT
Platform: UNKNOWN
Classifier: Programming Language :: Python :: 3
Classifier: License :: OSI Approved :: MIT License
Classifier: Operating System :: OS Independent
Requires-Python: >=3.6.0
Requires-Dist: nuclear
